hirundo/__init__.py
hirundo/__main__.py
hirundo/_constraints.py
hirundo/_dataframe.py
hirundo/_env.py
hirundo/_headers.py
hirundo/_http.py
hirundo/_iter_sse_retrying.py
hirundo/_timeouts.py
hirundo/_urls.py
hirundo/cli.py
hirundo/dataset_enum.py
hirundo/dataset_qa.py
hirundo/dataset_qa_results.py
hirundo/git.py
hirundo/labeling.py
hirundo/logger.py
hirundo/storage.py
hirundo/unzip.py
hirundo-0.1.21.dist-info/licenses/LICENSE
hirundo-0.1.21.dist-info/METADATA
hirundo-0.1.21.dist-info/WHEEL
hirundo-0.1.21.dist-info/entry_points.txt
hirundo-0.1.21.dist-info/top_level.txt
hirundo-0.1.21.dist-info/RECORD
