Metadata-Version: 2.4
Name: hirundo
Version: 0.1.21
Summary: This package is used to interface with Hirundo's platform. It provides a simple API to optimize your ML datasets.
Author-email: Hirundo <dev@hirundo.io>
License: MIT License
Project-URL: Homepage, https://github.com/Hirundo-io/hirundo-python-sdk
Keywords: dataset,machine learning,data science,data engineering
Classifier: License :: OSI Approved :: MIT License
Classifier: Programming Language :: Python
Classifier: Programming Language :: Python :: 3
Requires-Python: >=3.9
License-File: LICENSE
Requires-Dist: pyyaml>=6.0.1
Requires-Dist: types-PyYAML>=6.0.12
Requires-Dist: pydantic>=2.7.1
Requires-Dist: twine>=5.0.0
Requires-Dist: python-dotenv>=1.0.1
Requires-Dist: types-requests>=2.31.0
Requires-Dist: typer>=0.12.3
Requires-Dist: httpx>=0.27.0
Requires-Dist: stamina>=24.2.0
Requires-Dist: httpx-sse>=0.4.0
Requires-Dist: tqdm>=4.66.5
Requires-Dist: h11>=0.16.0
Requires-Dist: requests>=2.32.4
Requires-Dist: urllib3>=2.5.0
Requires-Dist: setuptools>=78.1.1
Provides-Extra: dev
Requires-Dist: pyyaml>=6.0.1; extra == "dev"
Requires-Dist: types-PyYAML>=6.0.12; extra == "dev"
Requires-Dist: pydantic>=2.7.1; extra == "dev"
Requires-Dist: twine>=5.0.0; extra == "dev"
Requires-Dist: python-dotenv>=1.0.1; extra == "dev"
Requires-Dist: types-requests>=2.31.0; extra == "dev"
Requires-Dist: types-setuptools>=69.5.0; extra == "dev"
Requires-Dist: typer>=0.12.3; extra == "dev"
Requires-Dist: httpx>=0.27.0; extra == "dev"
Requires-Dist: stamina>=24.2.0; extra == "dev"
Requires-Dist: httpx-sse>=0.4.0; extra == "dev"
Requires-Dist: pytest>=8.2.0; extra == "dev"
Requires-Dist: pytest-asyncio>=0.23.6; extra == "dev"
Requires-Dist: uv>=0.8.6; extra == "dev"
Requires-Dist: pre-commit>=3.7.1; extra == "dev"
Requires-Dist: virtualenv>=20.6.6; extra == "dev"
Requires-Dist: ruff>=0.12.0; extra == "dev"
Requires-Dist: bumpver; extra == "dev"
Requires-Dist: platformdirs>=4.3.6; extra == "dev"
Requires-Dist: safety>=3.2.13; extra == "dev"
Requires-Dist: cryptography>=44.0.1; extra == "dev"
Requires-Dist: jinja2>=3.1.6; extra == "dev"
Provides-Extra: docs
Requires-Dist: sphinx>=7.4.7; extra == "docs"
Requires-Dist: sphinx-autobuild>=2024.9.3; extra == "docs"
Requires-Dist: sphinx-click>=5.0.1; extra == "docs"
Requires-Dist: autodoc_pydantic>=2.2.0; extra == "docs"
Requires-Dist: furo; extra == "docs"
Requires-Dist: sphinx-multiversion; extra == "docs"
Requires-Dist: esbonio; extra == "docs"
Requires-Dist: starlette>=0.47.2; extra == "docs"
Requires-Dist: markupsafe>=3.0.2; extra == "docs"
Requires-Dist: jinja2>=3.1.6; extra == "docs"
Provides-Extra: pandas
Requires-Dist: pandas>=2.2.3; extra == "pandas"
Provides-Extra: polars
Requires-Dist: polars>=1.0.0; extra == "polars"
Dynamic: license-file
